balto/__init__.py
balto/compilation.py
balto/constants.py
balto/deprecations.py
balto/exceptions.py
balto/flags.py
balto/hooks.py
balto/internal_deprecations.py
balto/links.py
balto/mp_context.py
balto/node_types.py
balto/profiler.py
balto/py.typed
balto/selected_resources.py
balto/utils.py
balto/version.py
balto/adapters/__about__.py
balto/adapters/__init__.py
balto/adapters/cache.py
balto/adapters/capability.py
balto/adapters/factory.py
balto/adapters/protocol.py
balto/adapters/py.typed
balto/adapters/reference_keys.py
balto/adapters/utils.py
balto/adapters/base/__init__.py
balto/adapters/base/column.py
balto/adapters/base/connections.py
balto/adapters/base/impl.py
balto/adapters/base/meta.py
balto/adapters/base/plugin.py
balto/adapters/base/query_headers.py
balto/adapters/base/relation.py
balto/adapters/clients/__init__.py
balto/adapters/clients/jinja.py
balto/adapters/contracts/__init__.py
balto/adapters/contracts/connection.py
balto/adapters/contracts/macros.py
balto/adapters/contracts/relation.py
balto/adapters/events/__init__.py
balto/adapters/events/adapter_types_pb2.py
balto/adapters/events/base_types.py
balto/adapters/events/logging.py
balto/adapters/events/types.py
balto/adapters/exceptions/__init__.py
balto/adapters/exceptions/alias.py
balto/adapters/exceptions/cache.py
balto/adapters/exceptions/compilation.py
balto/adapters/exceptions/connection.py
balto/adapters/exceptions/database.py
balto/adapters/record/__init__.py
balto/adapters/record/handle.py
balto/adapters/record/cursor/cursor.py
balto/adapters/record/cursor/description.py
balto/adapters/record/cursor/execute.py
balto/adapters/record/cursor/fetchall.py
balto/adapters/record/cursor/fetchmany.py
balto/adapters/record/cursor/fetchone.py
balto/adapters/record/cursor/rowcount.py
balto/adapters/relation_configs/__init__.py
balto/adapters/relation_configs/config_base.py
balto/adapters/relation_configs/config_change.py
balto/adapters/relation_configs/config_validation.py
balto_core-0.1.7.dist-info/METADATA
balto_core-0.1.7.dist-info/WHEEL
balto_core-0.1.7.dist-info/entry_points.txt
balto_core-0.1.7.dist-info/top_level.txt
balto_core-0.1.7.dist-info/RECORD
