Metadata-Version: 2.2
Name: balto-core
Version: 0.1.7
Summary: With balto, data analysts and engineers can build analytics the way engineers build applications.
Home-page: https://github.com/balto-data/balto
Author: Balto Data
Author-email: support@baltodatatool.com
Classifier: Development Status :: 5 - Production/Stable
Classifier: License :: OSI Approved :: Apache Software License
Classifier: Operating System :: Microsoft :: Windows
Classifier: Operating System :: MacOS :: MacOS X
Classifier: Operating System :: POSIX :: Linux
Classifier: Programming Language :: Python :: 3.8
Classifier: Programming Language :: Python :: 3.9
Classifier: Programming Language :: Python :: 3.10
Classifier: Programming Language :: Python :: 3.11
Classifier: Programming Language :: Python :: 3.12
Requires-Python: >=3.8
Requires-Dist: agate<1.10,>=1.7.0
Requires-Dist: Jinja2<4,>=3.1.3
Requires-Dist: mashumaro[msgpack]<4.0,>=3.9
Requires-Dist: click<9.0,>=8.0.2
Requires-Dist: networkx<4.0,>=2.3
Requires-Dist: protobuf<5,>=4.0.0
Requires-Dist: requests<3.0.0
Requires-Dist: snowflake-connector-python[secure-local-storage]~=3.0
Requires-Dist: pathspec<0.13,>=0.9
Requires-Dist: sqlparse<0.6.0,>=0.5.0
Requires-Dist: dbt-extractor<=0.6,>=0.5.0
Requires-Dist: dbt-semantic-interfaces<0.8,>=0.7.0
Requires-Dist: dbt-common<2.0,>=1.6.0
Requires-Dist: packaging>20.9
Requires-Dist: pytz>=2015.7
Requires-Dist: pyyaml>=6.0
Requires-Dist: daff>=1.3.46
Requires-Dist: typing-extensions>=4.4
Dynamic: author
Dynamic: author-email
Dynamic: classifier
Dynamic: description
Dynamic: description-content-type
Dynamic: home-page
Dynamic: requires-dist
Dynamic: requires-python
Dynamic: summary
